posets/__init__.py
posets/examples.py
posets/hasseDiagram.py
posets/polynomial.py
posets/poset.py
posets/utils.py
posets-1.0.3.dist-info/METADATA
posets-1.0.3.dist-info/WHEEL
posets-1.0.3.dist-info/licenses/LICENSE
posets-1.0.3.dist-info/RECORD
