Metadata-Version: 2.4
Name: posets
Version: 1.0.3
Summary: A package for working with finite partial orders
Project-URL: Homepage, https://github.com/WilliamGustafson/posets
Project-URL: Documentation, https://github.com/WilliamGustafson/posets/releases/latest/download/posets.pdf
Author-email: William Gustafson <williamlgustafson@gmail.com>
License-File: LICENSE
Keywords: Hasse diagram,ab-index,cd-index,flag vectors,lattices,order complex,partial orders,partially ordered,partially ordered sets,posets
Classifier: License :: OSI Approved :: MIT License
Classifier: Operating System :: OS Independent
Classifier: Programming Language :: Python :: 3
Requires-Python: >=3.8
Requires-Dist: decorator
Requires-Dist: numpy
Requires-Dist: wand
